opero/__init__.py
opero/exceptions.py
opero/concurrency/__init__.py
opero/concurrency/pool.py
opero/core/__init__.py
opero/core/cache.py
opero/core/fallback.py
opero/core/rate_limit.py
opero/core/retry.py
opero/decorators/__init__.py
opero/decorators/opero.py
opero/decorators/opmap.py
opero/utils/__init__.py
opero/utils/async_utils.py
opero/utils/logging.py
opero-2.7.5.dist-info/METADATA
opero-2.7.5.dist-info/WHEEL
opero-2.7.5.dist-info/licenses/LICENSE
opero-2.7.5.dist-info/RECORD
