Metadata-Version: 2.4
Name: opero
Version: 2.7.5
Summary: Resilient, parallel task orchestration for Python
Project-URL: Documentation, https://github.com/twardoch/opero#readme
Project-URL: Issues, https://github.com/twardoch/opero/issues
Project-URL: Source, https://github.com/twardoch/opero
Author-email: Adam Twardoch <adam@twardoch.com>
License: MIT License
License-File: LICENSE
Keywords: concurrency,fallback,orchestration,parallel,rate-limiting,resilience,retry
Classifier: Development Status :: 4 - Beta
Classifier: Programming Language :: Python
Classifier: Programming Language :: Python :: 3.10
Classifier: Programming Language :: Python :: 3.11
Classifier: Programming Language :: Python :: 3.12
Classifier: Programming Language :: Python :: Implementation :: CPython
Classifier: Programming Language :: Python :: Implementation :: PyPy
Requires-Python: >=3.10
Requires-Dist: asynciolimiter>=1.0.0
Requires-Dist: tenacity>=8.0.0
Requires-Dist: twat-cache>=2.3.0
Requires-Dist: twat-mp>=2.6.0
Provides-Extra: aiomultiprocess
Requires-Dist: aiomultiprocess>=0.9.0; extra == 'aiomultiprocess'
Provides-Extra: all
Requires-Dist: aiomultiprocess>=0.9.0; extra == 'all'
Requires-Dist: pathos>=0.3.0; extra == 'all'
Provides-Extra: dev
Requires-Dist: black>=23.1.0; extra == 'dev'
Requires-Dist: mypy>=1.0.0; extra == 'dev'
Requires-Dist: pre-commit>=3.6.0; extra == 'dev'
Requires-Dist: ruff>=0.1.0; extra == 'dev'
Provides-Extra: pathos
Requires-Dist: pathos>=0.3.0; extra == 'pathos'
Provides-Extra: test
Requires-Dist: pytest-asyncio>=0.21.0; extra == 'test'
Requires-Dist: pytest-benchmark[histogram]>=4.0.0; extra == 'test'
Requires-Dist: pytest-cov>=4.0.0; extra == 'test'
Requires-Dist: pytest-xdist>=3.5.0; extra == 'test'
Requires-Dist: pytest>=7.0.0; extra == 'test'
